Workbook
Name Aporte: Tabela_financeira!$D$18
Name patrimonio: Tabela_financeira!$D$21
Name Qntd_anos: Tabela_financeira!$D$19
Name Rendimento_carteira: Tabela_financeira!$D$14
Name Salario: Tabela_financeira!$D$13
Name Sugestao_investimento: Tabela_financeira!$D$15
Name Taxa_mensal: Tabela_financeira!$D$20

Sheet Tabela_financeira
B12: CONFIGURAÇÕES
B13: Salário | D13: 2000
B14: Rendimento carteira | D14: 0.006
B15: Sugestão de investimento (30%) | D15: =30%*Salario -> 600
B17: INVESTIMENTO MENSAL
B18: Quanto investir por mês? | D18: 600
B19: Por quantos anos? | D19: 5
B20: Taxa de rendimento mensal? | D20: 0.01079
B21: Patrimônio acumulado? | D21: =FV(Taxa_mensal,Qntd_anos*12,Aporte*-1) -> 50266.148
B22: Dividendos mensais? | D22: =patrimonio*$D$14 -> 301.59689
B24: CENÁRIOS | D24: DIVIDENDO
A25: 2 | B25: Quanto em 2 anos? | C25: =FV($D$20,$A25*12,$D$18*-1) -> 16336.576 | D25: =C25*Rendimento_carteira -> 98.019458
A26: 5 | B26: Quanto em 5 anos? | C26: =FV($D$20,$A26*12,$D$18*-1) -> 50266.148 | D26: =C26*Rendimento_carteira -> 301.59689
A27: 10 | B27: Quanto em 10 anos? | C27: =FV($D$20,$A27*12,$D$18*-1) -> 145970.53 | D27: =C27*Rendimento_carteira -> 875.82317
A28: 20 | B28: Quanto em 20 anos? | C28: =FV($D$20,$A28*12,$D$18*-1) -> 675119.04 | D28: =C28*Rendimento_carteira -> 4050.7142
A29: 30 | B29: Quanto em 30 anos? | C29: =FV($D$20,$A29*12,$D$18*-1) -> 2593301.8 | D29: =C29*Rendimento_carteira -> 15559.811
B31: PERFIL | C31: AGRESSIVO
B32: Valor a ser investido por mês | C32: =Aporte -> 600
B34: Tipo de FII | C34: PERCENTUAL SUGERIDO | D34: VALORES
B35: PAPEL | C35: =VLOOKUP($C$31&"-"&B35,Tabela_de_apoio!$A$1:$D$20,4,FALSE) -> 0.5 | D35: =C35*$C$32 -> 300
B36: TIJOLO | C36: =VLOOKUP($C$31&"-"&B36,Tabela_de_apoio!$A:$D,4,FALSE) -> 0.1 | D36: =C36*$C$32 -> 60
B37: HÍBRIDOS | C37: =VLOOKUP($C$31&"-"&B37,Tabela_de_apoio!$A:$D,4,FALSE) -> 0.05 | D37: =C37*$C$32 -> 30
B38: FOFs | C38: =VLOOKUP($C$31&"-"&B38,Tabela_de_apoio!$A:$D,4,FALSE) -> 0.05 | D38: =C38*$C$32 -> 30
B39: DESENVOLVIMENTO | C39: =VLOOKUP($C$31&"-"&B39,Tabela_de_apoio!$A:$D,4,FALSE) -> 0.2 | D39: =C39*$C$32 -> 120
B40: HOTELÁRIAS | C40: =VLOOKUP($C$31&"-"&B40,Tabela_de_apoio!$A:$D,4,FALSE) -> 0.1 | D40: =C40*$C$32 -> 60
B41: TOTAL | D41: =SUM(D35:D40) -> 600

Sheet Tabela_de_apoio
A2: CHAVE | B2: PERFIL | C2: TIPO DE FII | D2: PERCENTUAL
A3: =B3&"-"&C3 -> CONSERVADOR-PAPEL | B3: CONSERVADOR | C3: PAPEL | D3: 0.3
A4: =B4&"-"&C4 -> CONSERVADOR-TIJOLO | B4: CONSERVADOR | C4: TIJOLO | D4: 0.5
A5: =B5&"-"&C5 -> CONSERVADOR-HÍBRIDOS | B5: CONSERVADOR | C5: HÍBRIDOS | D5: 0.1
A6: =B6&"-"&C6 -> CONSERVADOR-FOFs | B6: CONSERVADOR | C6: FOFs | D6: 0.1
A7: =B7&"-"&C7 -> CONSERVADOR-DESENVOLVIMENTO | B7: CONSERVADOR | C7: DESENVOLVIMENTO | D7: 0
A8: =B8&"-"&C8 -> CONSERVADOR-HOTELÁRIAS | B8: CONSERVADOR | C8: HOTELÁRIAS | D8: 0
A9: =B9&"-"&C9 -> MODERADO-PAPEL | B9: MODERADO | C9: PAPEL | D9: 0.32
A10: =B10&"-"&C10 -> MODERADO-TIJOLO | B10: MODERADO | C10: TIJOLO | D10: 0.35
A11: =B11&"-"&C11 -> MODERADO-HÍBRIDOS | B11: MODERADO | C11: HÍBRIDOS | D11: 0.08
A12: =B12&"-"&C12 -> MODERADO-FOFs | B12: MODERADO | C12: FOFs | D12: 0.05
A13: =B13&"-"&C13 -> MODERADO-DESENVOLVIMENTO | B13: MODERADO | C13: DESENVOLVIMENTO | D13: 0.1
A14: =B14&"-"&C14 -> MODERADO-HOTELÁRIAS | B14: MODERADO | C14: HOTELÁRIAS | D14: 0.1
... A20: =B20&"-"&C20 -> AGRESSIVO-HOTELÁRIAS | B20: AGRESSIVO | C20: HOTELÁRIAS | D20: 0.1
